smtpcomms.py
smtpcomms-2.dist-info/METADATA
smtpcomms-2.dist-info/WHEEL
smtpcomms-2.dist-info/top_level.txt
smtpcomms-2.dist-info/RECORD
