Metadata-Version: 2.1
Name: smtpcomms
Version: 2
Requires-Dist: requests
